compv/.DS_Store
compv/.env
compv/__init__.py
compv/ACI.py
compv/API_KEY.py
compv/APIS_components.py
compv/Call_specific_api_endpoint.py
compv/Checkwebservices.py
compv/create_endpoint.py
compv/CV3.egg-info/dependency_links.txt
compv/CV3.egg-info/entry_points.txt
compv/CV3.egg-info/PKG-INFO
compv/CV3.egg-info/requires.txt
compv/CV3.egg-info/SOURCES.txt
compv/CV3.egg-info/top_level.txt
compv/data_loading.py
compv/data_preprocessing.py
compv/Data_upload_stijn.py
compv/deploy_model.py
compv/endpoint_Creation.ipynb
compv/evaluation_images/img1.png
compv/evaluation_images/img2.png
compv/evaluation_images/img3.png
compv/evaluation_images/img4.png
compv/evaluation_images/img5.png
compv/evaluation_metrics.py
compv/instance_segmentation.py
compv/keys.json
compv/keys.py
compv/landmarks_detection.py
compv/main.py
compv/mask_prediction.py
compv/model_creation.py
compv/model_evaluation.py
compv/model_registration.py
compv/model_training.py
compv/README.md
compv/root_length_measurement.py
compv/score.py
compv/test_data_preprocessing.py
compv/test_evaluation.py
compv/utils.py
mark_processor-0.1.0.dist-info/METADATA
mark_processor-0.1.0.dist-info/WHEEL
mark_processor-0.1.0.dist-info/RECORD
