Metadata-Version: 2.1
Name: mark-processor
Version: 0.1.0
Summary: 
Author: neildaniel221270
Author-email: 112754523+neildaniel221270@users.noreply.github.com
Requires-Python: >=3.8.13,<3.10.4
Classifier: Programming Language :: Python :: 3
Classifier: Programming Language :: Python :: 3.9
Classifier: Programming Language :: Python :: 3.10
Requires-Dist: azure-ai-ml (>=1.4.0,<2.0.0)
Requires-Dist: azure-identity (>=1.12.0,<2.0.0)
Requires-Dist: azureml-core (>=1.50.0,<1.57.0)
Requires-Dist: azureml-inference-server-http (>=0.1.5)
Requires-Dist: azureml-mlflow (==1.56.0)
Requires-Dist: fastapi (>=0.95.0)
Requires-Dist: geopandas (>=0.13.0,<0.14.0)
Requires-Dist: keras (>=2.8.0,<3.0.0)
Requires-Dist: matplotlib (>=3.9.0,<4.0.0) ; python_version >= "3.9" and python_full_version < "3.10.4"
Requires-Dist: mlflow (>1.20.0,<2.13.1)
Requires-Dist: networkx (>=2.7.1,<4.0.0)
Requires-Dist: numpy (>=1.24.3,<2.0.0)
Requires-Dist: opencensus-ext-azure (==1.1.13)
Requires-Dist: opencv-python-headless (>=4.7.0.72,<5.0.0.0)
Requires-Dist: pandas (>=2.0.2,<3.0.0)
Requires-Dist: patchify (>=0.2.3,<0.3.0)
Requires-Dist: plotly (>=5.14.1,<6.0.0)
Requires-Dist: poetry2conda (>=0.3.0,<0.4.0)
Requires-Dist: pre-commit (>=3.2.0,<4.0.0)
Requires-Dist: requests (>=2.31.0,<3.0.0)
Requires-Dist: scikit-image (>=0.21.0,<0.22.0)
Requires-Dist: scikit-learn (>=1.2.2,<2.0.0)
Requires-Dist: seaborn (>=0.1,<0.13.3)
Requires-Dist: skan (>=0.1,<0.11.1)
Requires-Dist: tensorflow (==2.10)
Requires-Dist: torch (>=1.0.0)
Requires-Dist: torchvision (>=0.15.1,<0.16.0)
Requires-Dist: tqdm (>=4.65.0,<5.0.0)
Requires-Dist: typer (>=0.12.3,<0.13.0)
